WkMysql/WkMysql.py
WkMysql/WkMysqlPool.py
WkMysql/__init__.py
WkMysql-1.1.2.2.dist-info/LICENSE
WkMysql-1.1.2.2.dist-info/METADATA
WkMysql-1.1.2.2.dist-info/WHEEL
WkMysql-1.1.2.2.dist-info/top_level.txt
WkMysql-1.1.2.2.dist-info/RECORD
