Metadata-Version: 2.1
Name: WkMysql
Version: 1.1.2.2
Summary: The secondary encapsulation of pymysql provides a more user-friendly interface and thread pool, and will support SQLite in the future.
Home-page: https://gitee.com/purify_wang/wk-mysql
Author: WANGKANG
Author-email: 1686617586@qq.com
License: GPL-2.0
Platform: all
Classifier: Intended Audience :: Developers
Classifier: Operating System :: OS Independent
Classifier: Natural Language :: Chinese (Simplified)
Classifier: Programming Language :: Python
Classifier: Programming Language :: Python :: 3
Classifier: Programming Language :: Python :: 3.10
Classifier: Programming Language :: Python :: 3.11
Classifier: Programming Language :: Python :: 3.12
Classifier: Topic :: Software Development :: Libraries
Requires-Python: >=3.10.0
License-File: LICENSE
Requires-Dist: pymysql
Requires-Dist: WkLog
